string_fixer/__init__.py
string_fixer/__main__.py
string_fixer/_version.py
string_fixer/config.py
string_fixer-0.5.0.dist-info/METADATA
string_fixer-0.5.0.dist-info/WHEEL
string_fixer-0.5.0.dist-info/top_level.txt
string_fixer-0.5.0.dist-info/RECORD
