Metadata-Version: 2.2
Name: string_fixer
Version: 0.5.0
Summary: Change quote style in Python files
Author-email: Crozzers <captaincrozzers@gmail.com>
License: MIT
Project-URL: Source, https://github.com/Crozzers/string-fixer
Project-URL: Issues, https://github.com/Crozzers/string-fixer/issues
Project-URL: Changelog, https://github.com/Crozzers/string-fixer/blob/main/lib/CHANGELOG.md
Classifier: Development Status :: 3 - Alpha
Classifier: License :: OSI Approved :: MIT License
Classifier: Operating System :: Microsoft :: Windows :: Windows 10
Classifier: Operating System :: Microsoft :: Windows :: Windows 11
Classifier: Operating System :: POSIX :: Linux
Classifier: Programming Language :: Python :: 3 :: Only
Requires-Python: >=3.8
Requires-Dist: libcst
Requires-Dist: tomli
Provides-Extra: dev
Requires-Dist: ruff; extra == "dev"
Provides-Extra: test
Requires-Dist: pytest; extra == "test"
Requires-Dist: pytest-snapshot; extra == "test"
Provides-Extra: dist
Requires-Dist: build; extra == "dist"
Requires-Dist: setuptools; extra == "dist"
Requires-Dist: wheel; extra == "dist"
Requires-Dist: twine; extra == "dist"
Provides-Extra: all
Requires-Dist: string_fixer[dev,dist,test]; extra == "all"
